pulumi_terraform/__init__.py
pulumi_terraform/_utilities.py
pulumi_terraform/provider.py
pulumi_terraform/pulumi-plugin.json
pulumi_terraform/py.typed
pulumi_terraform/state/__init__.py
pulumi_terraform/state/_inputs.py
pulumi_terraform/state/get_local_reference.py
pulumi_terraform/state/get_remote_reference.py
pulumi_terraform-6.0.0.dist-info/METADATA
pulumi_terraform-6.0.0.dist-info/WHEEL
pulumi_terraform-6.0.0.dist-info/top_level.txt
pulumi_terraform-6.0.0.dist-info/RECORD
