Metadata-Version: 2.4
Name: pulumi_terraform
Version: 6.0.0
Summary: The Terraform provider for Pulumi lets you consume the outputs contained in Terraform state from your Pulumi programs.
License: Apache-2.0
Project-URL: Homepage, https://pulumi.com
Project-URL: Repository, https://github.com/pulumi/pulumi-terraform
Keywords: terraform,kind/native,category/utility
Requires-Python: >=3.9
Requires-Dist: parver>=0.2.1
Requires-Dist: pulumi<4.0.0,>=3.142.0
Requires-Dist: semver>=2.8.1
Requires-Dist: typing-extensions>=4.11; python_version < "3.11"
